LICENSE
MANIFEST.in
README.md
setup.py
silentor/.git
silentor/404.md
silentor/LICENSE
silentor/README.md
silentor/config.json
silentor/default_config.json
silentor/favicon.ico
silentor/index.html
silentor/img/favicon.ico
silentor/p/about.md
silentor/p/footer.md
silentor/p/home.md
silentor/p/profession.md
silentor/p/sidebar.md
silentor/p/Authors/jayin.md
silentor/p/projects/ETips.md
silentor/p/projects/index.md
silentor/vendor/blog.css
silentor/vendor/blog.js
silentor/vendor/github-markdown.css
silentor/vendor/jquery-1.11.1.min.js
silentor/vendor/marked-0.3.2.min.js
silentor/vendor/highlight/CHANGES.md
silentor/vendor/highlight/LICENSE
silentor/vendor/highlight/README.md
silentor/vendor/highlight/README.ru.md
silentor/vendor/highlight/highlight.pack.js
silentor/vendor/highlight/styles/arta.css
silentor/vendor/highlight/styles/ascetic.css
silentor/vendor/highlight/styles/atelier-dune.dark.css
silentor/vendor/highlight/styles/atelier-dune.light.css
silentor/vendor/highlight/styles/atelier-forest.dark.css
silentor/vendor/highlight/styles/atelier-forest.light.css
silentor/vendor/highlight/styles/atelier-heath.dark.css
silentor/vendor/highlight/styles/atelier-heath.light.css
silentor/vendor/highlight/styles/atelier-lakeside.dark.css
silentor/vendor/highlight/styles/atelier-lakeside.light.css
silentor/vendor/highlight/styles/atelier-seaside.dark.css
silentor/vendor/highlight/styles/atelier-seaside.light.css
silentor/vendor/highlight/styles/brown_paper.css
silentor/vendor/highlight/styles/brown_papersq.png
silentor/vendor/highlight/styles/codepen-embed.css
silentor/vendor/highlight/styles/color-brewer.css
silentor/vendor/highlight/styles/dark.css
silentor/vendor/highlight/styles/default.css
silentor/vendor/highlight/styles/docco.css
silentor/vendor/highlight/styles/far.css
silentor/vendor/highlight/styles/foundation.css
silentor/vendor/highlight/styles/github.css
silentor/vendor/highlight/styles/googlecode.css
silentor/vendor/highlight/styles/hybrid.css
silentor_cli.egg-info/PKG-INFO
silentor_cli.egg-info/SOURCES.txt
silentor_cli.egg-info/dependency_links.txt
silentor_cli.egg-info/entry_points.txt
silentor_cli.egg-info/requires.txt
silentor_cli.egg-info/top_level.txt
