Metadata-Version: 1.1
Name: silentor-cli
Version: 0.1.0
Summary: the command line interface for silentor
Home-page: http://github.com/jayin/silentorcli-cli
Author: Jayin Ton
Author-email: tonjayin@gmail.com
License: UNKNOWN
Platform: UNKNOWN
Classifier: License :: OSI Approved :: MIT License
Classifier: Programming Language :: Python
Classifier: Programming Language :: Python :: 2
